{
    "key": "group_61b16dabc6747",
    "title": "Options - Options Fields",
    "fields": [
        {
            "key": "field_61b16f17a3c26",
            "label": "Site Options",
            "name": "site_options",
            "type": "group",
            "instructions": "",
            "required": 0,
            "conditional_logic": 0,
            "wrapper": {
                "width": "",
                "class": "",
                "id": ""
            },
            "layout": "block",
            "wpml_cf_preferences": 3,
            "acfe_seamless_style": 0,
            "acfe_group_modal": 0,
            "sub_fields": [
                {
                    "key": "field_61b16df12db13",
                    "label": "Copyright",
                    "name": "copyright",
                    "type": "text",
                    "instructions": "",
                    "required": 0,
                    "conditional_logic": 0,
                    "wrapper": {
                        "width": "",
                        "class": "",
                        "id": ""
                    },
                    "wpml_cf_preferences": 3,
                    "default_value": "",
                    "placeholder": "",
                    "prepend": "",
                    "append": "",
                    "maxlength": ""
                }
            ]
        }
    ],
    "location": [
        [
            {
                "param": "options_page",
                "operator": "==",
                "value": "site-options"
            }
        ]
    ],
    "menu_order": 0,
    "position": "normal",
    "style": "default",
    "label_placement": "left",
    "instruction_placement": "label",
    "hide_on_screen": "",
    "active": true,
    "description": "",
    "show_in_rest": 0,
    "acfe_display_title": "",
    "acfe_autosync": [
        "json"
    ],
    "acfe_form": 0,
    "acfe_meta": "",
    "acfe_note": "",
    "modified": 1639018350,
    "acfe_categories": {
        "options": "Options"
    }
}